[
  {
    "__type__": "cc.SpriteFrame",
    "content": {
      "name": "default_btn_disabled",
      "texture": "71VhFCTINJM6/Ky3oX9nBT",
      "rect": [
        0,
        0,
        40,
        40
      ],
      "offset": [
        0,
        0
      ],
      "originalSize": [
        40,
        40
      ],
      "capInsets": [
        12,
        12,
        12,
        12
      ]
    }
  },
  {
    "__type__": "cc.SpriteFrame",
    "content": {
      "name": "birdbox1",
      "texture": "f3mR5t02hNT5mxIYH1pA1t",
      "rect": [
        1,
        2,
        97,
        97
      ],
      "offset": [
        -0.5,
        -0.5
      ],
      "originalSize": [
        100,
        100
      ],
      "capInsets": [
        0,
        0,
        0,
        0
      ]
    }
  },
  {
    "__type__": "cc.SpriteFrame",
    "content": {
      "name": "birdbox2",
      "texture": "dd9AxyyF1OAbRXeT5bV5wF",
      "rect": [
        1,
        2,
        97,
        97
      ],
      "offset": [
        -0.5,
        -0.5
      ],
      "originalSize": [
        100,
        100
      ],
      "capInsets": [
        0,
        0,
        0,
        0
      ]
    }
  },
  [
    {
      "__type__": "cc.Prefab",
      "_name": "bird_element",
      "data": {
        "__id__": 1
      }
    },
    {
      "__type__": "cc.Node",
      "_name": "bird_element",
      "_children": [
        {
          "__id__": 2
        },
        {
          "__id__": 3
        },
        {
          "__id__": 4
        },
        {
          "__id__": 6
        },
        {
          "__id__": 8
        }
      ],
      "_components": [
        {
          "__type__": "c8c60LW8XVCJYlF9QKbE//E",
          "node": {
            "__id__": 1
          },
          "boxs": [
            {
              "__id__": 2
            },
            {
              "__id__": 3
            }
          ],
          "icon": {
            "__id__": 5
          },
          "btn": {
            "__id__": 7
          },
          "unlock": {
            "__id__": 9
          }
        }
      ],
      "_prefab": {
        "__type__": "cc.PrefabInfo",
        "root": {
          "__id__": 1
        },
        "asset": {
          "__uuid__": "7eCTN8U5NFRrHJtRiRHARx"
        },
        "fileId": "59d3ePxgxhP17q/bKZe2Mkj"
      },
      "_contentSize": {
        "__type__": "cc.Size",
        "width": 98,
        "height": 98
      },
      "_trs": {
        "__type__": "TypedArray",
        "ctor": "Float64Array",
        "array": [
          0,
          0,
          0,
          0,
          0,
          0,
          1,
          1,
          1,
          1
        ]
      }
    },
    {
      "__type__": "cc.Node",
      "_name": "birdbox1",
      "_parent": {
        "__id__": 1
      },
      "_components": [
        {
          "__type__": "cc.Sprite",
          "node": {
            "__id__": 2
          },
          "_materials": [
            {
              "__uuid__": "ecpdLyjvZBwrvm+cedCcQy"
            }
          ],
          "_spriteFrame": {
            "__uuid__": "73ZQaN9PZMhYKPobKZPpH5"
          }
        }
      ],
      "_prefab": {
        "__type__": "cc.PrefabInfo",
        "root": {
          "__id__": 1
        },
        "asset": {
          "__uuid__": "7eCTN8U5NFRrHJtRiRHARx"
        },
        "fileId": "aeDVAxM8xOIpXm6c8Ugz1b"
      },
      "_contentSize": {
        "__type__": "cc.Size",
        "width": 97,
        "height": 98
      },
      "_trs": {
        "__type__": "TypedArray",
        "ctor": "Float64Array",
        "array": [
          0,
          0,
          0,
          0,
          0,
          0,
          1,
          1,
          1,
          1
        ]
      }
    },
    {
      "__type__": "cc.Node",
      "_name": "birdbox2",
      "_parent": {
        "__id__": 1
      },
      "_active": false,
      "_components": [
        {
          "__type__": "cc.Sprite",
          "node": {
            "__id__": 3
          },
          "_materials": [
            {
              "__uuid__": "ecpdLyjvZBwrvm+cedCcQy"
            }
          ],
          "_spriteFrame": {
            "__uuid__": "7alLF8PEVE4aY89T7Tj3Qu"
          }
        }
      ],
      "_prefab": {
        "__type__": "cc.PrefabInfo",
        "root": {
          "__id__": 1
        },
        "asset": {
          "__uuid__": "7eCTN8U5NFRrHJtRiRHARx"
        },
        "fileId": "88CJFHTF9HHpoCtXAH0wFP"
      },
      "_contentSize": {
        "__type__": "cc.Size",
        "width": 97,
        "height": 98
      },
      "_trs": {
        "__type__": "TypedArray",
        "ctor": "Float64Array",
        "array": [
          0,
          0,
          0,
          0,
          0,
          0,
          1,
          1,
          1,
          1
        ]
      }
    },
    {
      "__type__": "cc.Node",
      "_name": "icon",
      "_parent": {
        "__id__": 1
      },
      "_components": [
        {
          "__id__": 5
        }
      ],
      "_prefab": {
        "__type__": "cc.PrefabInfo",
        "root": {
          "__id__": 1
        },
        "asset": {
          "__uuid__": "7eCTN8U5NFRrHJtRiRHARx"
        },
        "fileId": "caUXae/QhOPKXoBvGSK01S"
      },
      "_contentSize": {
        "__type__": "cc.Size",
        "width": 98,
        "height": 98
      },
      "_trs": {
        "__type__": "TypedArray",
        "ctor": "Float64Array",
        "array": [
          0,
          0,
          0,
          0,
          0,
          0,
          1,
          1,
          1,
          1
        ]
      }
    },
    {
      "__type__": "cc.Sprite",
      "_name": "icon<Sprite>",
      "node": {
        "__id__": 4
      },
      "_materials": [
        {
          "__uuid__": "ecpdLyjvZBwrvm+cedCcQy"
        }
      ]
    },
    {
      "__type__": "cc.Node",
      "_name": "btn",
      "_parent": {
        "__id__": 1
      },
      "_components": [
        {
          "__id__": 7
        }
      ],
      "_prefab": {
        "__type__": "cc.PrefabInfo",
        "root": {
          "__id__": 1
        },
        "asset": {
          "__uuid__": "7eCTN8U5NFRrHJtRiRHARx"
        },
        "fileId": "6bIUHbRG5JAo5Gn/KCIyUC"
      },
      "_color": {
        "__type__": "cc.Color",
        "r": 230,
        "g": 230,
        "b": 230
      },
      "_contentSize": {
        "__type__": "cc.Size",
        "width": 98,
        "height": 98
      },
      "_trs": {
        "__type__": "TypedArray",
        "ctor": "Float64Array",
        "array": [
          0,
          0,
          0,
          0,
          0,
          0,
          1,
          1,
          1,
          1
        ]
      }
    },
    {
      "__type__": "cc.Button",
      "node": {
        "__id__": 6
      },
      "clickEvents": [
        {
          "__type__": "cc.ClickEvent",
          "target": {
            "__id__": 1
          },
          "_componentId": "c8c60LW8XVCJYlF9QKbE//E",
          "handler": "onClickButton"
        }
      ],
      "_N$normalColor": {
        "__type__": "cc.Color",
        "r": 230,
        "g": 230,
        "b": 230
      },
      "_N$pressedColor": {
        "__type__": "cc.Color",
        "r": 200,
        "g": 200,
        "b": 200
      },
      "pressedColor": {
        "__type__": "cc.Color",
        "r": 200,
        "g": 200,
        "b": 200
      },
      "_N$disabledColor": {
        "__type__": "cc.Color",
        "r": 120,
        "g": 120,
        "b": 120,
        "a": 200
      },
      "_N$normalSprite": {
        "__uuid__": "f0BIwQ8D5Ml7nTNQbh1YlS"
      },
      "_N$pressedSprite": {
        "__uuid__": "e97GVMl6JHh5Ml5qEDdSGa"
      },
      "pressedSprite": {
        "__uuid__": "e97GVMl6JHh5Ml5qEDdSGa"
      },
      "_N$hoverSprite": {
        "__uuid__": "f0BIwQ8D5Ml7nTNQbh1YlS"
      },
      "hoverSprite": {
        "__uuid__": "f0BIwQ8D5Ml7nTNQbh1YlS"
      },
      "_N$disabledSprite": {
        "__uuid__": "29FYIk+N1GYaeWH/q1NxQO"
      }
    },
    {
      "__type__": "cc.Node",
      "_name": "unlock",
      "_parent": {
        "__id__": 1
      },
      "_active": false,
      "_components": [
        {
          "__id__": 9
        }
      ],
      "_prefab": {
        "__type__": "cc.PrefabInfo",
        "root": {
          "__id__": 1
        },
        "asset": {
          "__uuid__": "7eCTN8U5NFRrHJtRiRHARx"
        },
        "fileId": "25IFp1WcVOkImMvVGWpiWQ"
      },
      "_contentSize": {
        "__type__": "cc.Size",
        "width": 160,
        "height": 50.4
      },
      "_trs": {
        "__type__": "TypedArray",
        "ctor": "Float64Array",
        "array": [
          0,
          -90.063,
          0,
          0,
          0,
          0,
          1,
          1,
          1,
          1
        ]
      }
    },
    {
      "__type__": "cc.Label",
      "_name": "unlock<Label>",
      "node": {
        "__id__": 8
      },
      "_materials": [
        {
          "__uuid__": "ecpdLyjvZBwrvm+cedCcQy"
        }
      ],
      "_useOriginalSize": false,
      "_string": "点击解锁",
      "_N$string": "点击解锁",
      "_fontSize": 32,
      "_lineHeight": 32,
      "_N$horizontalAlign": 1,
      "_N$verticalAlign": 1
    }
  ],
  {
    "__type__": "cc.SpriteFrame",
    "content": {
      "name": "default_btn_pressed",
      "texture": "b4P/PCArtIdIH38t6mlw8Y",
      "rect": [
        0,
        0,
        40,
        40
      ],
      "offset": [
        0,
        0
      ],
      "originalSize": [
        40,
        40
      ],
      "capInsets": [
        12,
        12,
        12,
        12
      ]
    }
  },
  {
    "__type__": "cc.SpriteFrame",
    "content": {
      "name": "default_btn_normal",
      "texture": "e8Ueib+qJEhL6mXAHdnwbi",
      "rect": [
        0,
        0,
        40,
        40
      ],
      "offset": [
        0,
        0
      ],
      "originalSize": [
        40,
        40
      ],
      "capInsets": [
        12,
        12,
        12,
        12
      ]
    }
  }
]